apiera/__init__.py
apiera/app.py
apiera/logger.py
apiera-0.0.11.dist-info/LICENSE
apiera-0.0.11.dist-info/WHEEL
apiera-0.0.11.dist-info/METADATA
apiera-0.0.11.dist-info/RECORD
