Metadata-Version: 2.1
Name: apiera
Version: 0.0.11
Summary: Apiera framework, high performance
Home-page: https://github.com/JeromeK13/hapi
License: UNKNOWN
Author: Jérôme Krell
Author-email: jerome.krell@bluewin.ch
Classifier: License :: OSI Approved :: MIT License
Requires-Dist: click==7.1.2
Requires-Dist: Cython==0.29.21
Requires-Dist: h11==0.9.0
Requires-Dist: starlette==0.13.8
Requires-Dist: uvicorn==0.11.8
Requires-Dist: websockets==8.1
